odoo/addons/mis_builder_analytic/README.rst
odoo/addons/mis_builder_analytic/__init__.py
odoo/addons/mis_builder_analytic/__manifest__.py
odoo/addons/mis_builder_analytic/i18n/mis_builder_analytic.pot
odoo/addons/mis_builder_analytic/i18n/pt_BR.po
odoo/addons/mis_builder_analytic/models/__init__.py
odoo/addons/mis_builder_analytic/models/mis_account_analytic_line.py
odoo/addons/mis_builder_analytic/readme/CONTRIBUTORS.rst
odoo/addons/mis_builder_analytic/readme/DESCRIPTION.rst
odoo/addons/mis_builder_analytic/readme/USAGE.rst
odoo/addons/mis_builder_analytic/security/ir.model.access.csv
odoo/addons/mis_builder_analytic/static/description/icon.png
odoo/addons/mis_builder_analytic/static/description/index.html
odoo/addons/mis_builder_analytic/views/mis_account_analytic_line_views.xml
odoo12_addon_mis_builder_analytic-12.0.1.0.0.99.dev7.dist-info/METADATA
odoo12_addon_mis_builder_analytic-12.0.1.0.0.99.dev7.dist-info/WHEEL
odoo12_addon_mis_builder_analytic-12.0.1.0.0.99.dev7.dist-info/top_level.txt
odoo12_addon_mis_builder_analytic-12.0.1.0.0.99.dev7.dist-info/RECORD
